{
  "features": [
    {
      "type": "Feature",
      "properties": {
        "title": "Delhi",
        "description": ""
      },
      "geometry": {
        "coordinates": [77.23, 28.66],
        "type": "Point"
      }
    },
    {
      "type": "Feature",
      "properties": {
        "title": "Mumbai",
        "description": "A lakefront park on Chicago's south side"
      },
      "geometry": {
        "coordinates": [72.877426, 19.07609],
        "type": "Point"
      }
    },
    {
      "type": "Feature",
      "properties": {
        "title": "Ahmedabad",
        "description": "A lakefront park on Chicago's south side"
      },
      "geometry": {
        "coordinates": [72.58, 23.03],
        "type": "Point"
      }
    },
    {
      "type": "Feature",
      "properties": {
        "title": "Hyderabad",
        "description": "A lakefront park on Chicago's south side"
      },
      "geometry": {
        "coordinates": [78.4667, 17.3667],
        "type": "Point"
      }
    },
    {
      "type": "Feature",
      "properties": {
        "title": "Indore",
        "description": "A lakefront park on Chicago's south side"
      },
      "geometry": {
        "coordinates": [75.8472, 22.7206],
        "type": "Point"
      }
    },
    {
      "type": "Feature",
      "properties": {
        "title": "Bangalore",
        "description": "A lakefront park on Chicago's south side"
      },
      "geometry": {
        "coordinates": [77.598, 12.9699],
        "type": "Point"
      }
    },
    {
      "type": "Feature",
      "properties": {
        "title": "Raipur",
        "description": "A lakefront park on Chicago's south side"
      },
      "geometry": {
        "coordinates": [81.6337, 21.2379],
        "type": "Point"
      }
    },
    {
      "type": "Feature",
      "properties": {
        "title": "Raipur",
        "description": "A lakefront park on Chicago's south side"
      },
      "geometry": {
        "coordinates": [81.6337, 21.2379],
        "type": "Point"
      }
    },
    {
      "type": "Feature",
      "properties": {
        "title": "Patna",
        "description": "A lakefront park on Chicago's south side"
      },
      "geometry": {
        "coordinates": [85.1414, 25.61],
        "type": "Point"
      }
    },
    {
      "type": "Feature",
      "properties": {
        "title": "Jodhpur",
        "description": "A lakefront park on Chicago's south side"
      },
      "geometry": {
        "coordinates": [73.0168, 26.2918],
        "type": "Point"
      }
    },
    {
      "type": "Feature",
      "properties": {
        "title": "Prayagraj",
        "description": "A lakefront park on Chicago's south side"
      },
      "geometry": {
        "coordinates": [81.84655982652886, 25.437923396548047],
        "type": "Point"
      }
    }
  ],
  "type": "FeatureCollection"
}
